ftptsgame/__init__.py
ftptsgame/database.py
ftptsgame/exceptions.py
ftptsgame/expr_utils.py
ftptsgame/problem_utils.py
42Points-1.2.7.dist-info/LICENSE
42Points-1.2.7.dist-info/METADATA
42Points-1.2.7.dist-info/WHEEL
42Points-1.2.7.dist-info/top_level.txt
42Points-1.2.7.dist-info/RECORD
